book.py
naver_book_query.py
setup.py
Naver_Book_Query.egg-info/PKG-INFO
Naver_Book_Query.egg-info/SOURCES.txt
Naver_Book_Query.egg-info/dependency_links.txt
Naver_Book_Query.egg-info/top_level.txt