Metadata-Version: 1.1
Name: Naver-Book-Query
Version: 0.9.1
Summary: Use naver book query like sqlalchemy
Home-page: https://github.com/kjisoo/naver_book_query
Author: Kim jisoo
Author-email: kim@jisoo.net
License: MIT License
Platform: UNKNOWN
Classifier: Programming Language :: Python :: 3 :: Only
Classifier: Programming Language :: Python :: 3.4
Classifier: Programming Language :: Python :: 3.5
